MANIFEST.in
README.rst
VERSION
requirements.txt
setup.py
src/flask_kser/__init__.py
src/flask_kser.egg-info/PKG-INFO
src/flask_kser.egg-info/SOURCES.txt
src/flask_kser.egg-info/dependency_links.txt
src/flask_kser.egg-info/requires.txt
src/flask_kser.egg-info/top_level.txt
src/flask_kser.egg-info/zip-safe