Metadata-Version: 1.1
Name: flask-kser
Version: 0.1.1
Summary: Flask KSer example
Home-page: https://github.com/cdumay/flask-kser
Author: Cedric DUMAY
Author-email: cedric.dumay@gmail.com
License: MIT
Platform: UNKNOWN
Classifier: Programming Language :: Python
